CONTRIBUTING.md
MANIFEST.in
README.rst
setup.py
docs/HISTORY.txt
docs/LICENSE.GPL
docs/LICENSE.txt
eea/__init__.py
eea.api.objectprovides.egg-info/PKG-INFO
eea.api.objectprovides.egg-info/SOURCES.txt
eea.api.objectprovides.egg-info/dependency_links.txt
eea.api.objectprovides.egg-info/entry_points.txt
eea.api.objectprovides.egg-info/namespace_packages.txt
eea.api.objectprovides.egg-info/not-zip-safe
eea.api.objectprovides.egg-info/requires.txt
eea.api.objectprovides.egg-info/top_level.txt
eea/api/__init__.py
eea/api/objectprovides/README.txt
eea/api/objectprovides/__init__.py
eea/api/objectprovides/configure.zcml
eea/api/objectprovides/interfaces.py
eea/api/objectprovides/object_provides.py
eea/api/objectprovides/profiles.zcml
eea/api/objectprovides/setuphandlers.py
eea/api/objectprovides/version.txt
eea/api/objectprovides/browser/__init__.py
eea/api/objectprovides/browser/configure.zcml
eea/api/objectprovides/locales/__init__.py
eea/api/objectprovides/locales/eea.pot
eea/api/objectprovides/locales/plone-manual.pot
eea/api/objectprovides/locales/update.sh
eea/api/objectprovides/locales/bg/LC_MESSAGES/eea.po
eea/api/objectprovides/locales/bg/LC_MESSAGES/plone.po
eea/api/objectprovides/locales/cs/LC_MESSAGES/eea.po
eea/api/objectprovides/locales/cs/LC_MESSAGES/plone.po
eea/api/objectprovides/locales/da/LC_MESSAGES/eea.po
eea/api/objectprovides/locales/da/LC_MESSAGES/plone.po
eea/api/objectprovides/locales/de/LC_MESSAGES/eea.po
eea/api/objectprovides/locales/de/LC_MESSAGES/plone.po
eea/api/objectprovides/locales/el/LC_MESSAGES/eea.po
eea/api/objectprovides/locales/el/LC_MESSAGES/plone.po
eea/api/objectprovides/locales/en/LC_MESSAGES/eea.po
eea/api/objectprovides/locales/en/LC_MESSAGES/plone.po
eea/api/objectprovides/locales/es/LC_MESSAGES/eea.po
eea/api/objectprovides/locales/es/LC_MESSAGES/plone.po
eea/api/objectprovides/locales/et/LC_MESSAGES/eea.po
eea/api/objectprovides/locales/et/LC_MESSAGES/plone.po
eea/api/objectprovides/locales/eu/LC_MESSAGES/eea.po
eea/api/objectprovides/locales/eu/LC_MESSAGES/plone.po
eea/api/objectprovides/locales/fi/LC_MESSAGES/eea.po
eea/api/objectprovides/locales/fi/LC_MESSAGES/plone.po
eea/api/objectprovides/locales/fr/LC_MESSAGES/eea.po
eea/api/objectprovides/locales/fr/LC_MESSAGES/plone.po
eea/api/objectprovides/locales/hr/LC_MESSAGES/eea.po
eea/api/objectprovides/locales/hr/LC_MESSAGES/plone.po
